[
  {
    "uid": 4256384715,
    "password": "jsnsjd_C53V8DJZLP0",
    "account_id": "13713081250",
    "name": "gblike⁴³⁴⁴³",
    "region": "BD",
    "status": "activated"
  },
  {
    "uid": 4256384340,
    "password": "jsnsjd_9Y33E3QFQ36",
    "account_id": "13713079242",
    "name": "gblike³⁷⁸³⁰",
    "region": "BD",
    "status": "activated"
  },
  {
    "uid": 4256384430,
    "password": "jsnsjd_2BTWJHIKJCM",
    "account_id": "13713079672",
    "name": "gblike³⁷²¹¹",
    "region": "BD",
    "status": "activated"
  },
  {
    "uid": 4256384341,
    "password": "jsnsjd_2OF1SCD92ER",
    "account_id": "13713079119",
    "name": "gblike¹⁸⁴⁵⁷",
    "region": "BD",
    "status": "activated"
  },
  {
    "uid": 4256384678,
    "password": "jsnsjd_VQG1IX5ILWZ",
    "account_id": "13713080924",
    "name": "gblike¹⁹²¹⁶",
    "region": "BD",
    "status": "activated"
  },
  {
    "uid": 4256384609,
    "password": "jsnsjd_DZ5KRKAQKK3",
    "account_id": "13713080490",
    "name": "gblike³⁸⁵³⁴",
    "region": "BD",
    "status": "activated"
  },
  {
    "uid": 4256384529,
    "password": "jsnsjd_C2GABPMERFE",
    "account_id": "13713080267",
    "name": "gblike⁷⁹⁵⁹⁸",
    "region": "BD",
    "status": "activated"
  },
  {
    "uid": 4256384528,
    "password": "jsnsjd_IBX4QYZ4YF6",
    "account_id": "13713080030",
    "name": "gblike¹⁶⁴⁴⁹",
    "region": "BD",
    "status": "activated"
  },
  {
    "uid": 4256384917,
    "password": "jsnsjd_BJAD0XFO9VQ",
    "account_id": "13713082053",
    "name": "gblike⁷²⁵⁶⁹",
    "region": "BD",
    "status": "activated"
  },
  {
    "uid": 4256384859,
    "password": "jsnsjd_XJRIECZ57K5",
    "account_id": "13713081870",
    "name": "gblike⁰²⁰⁸⁴",
    "region": "BD",
    "status": "activated"
  },
  {
    "uid": 4256384931,
    "password": "jsnsjd_5INO1ZSTAOO",
    "account_id": "13713082157",
    "name": "gblike²⁷³⁷⁹",
    "region": "BD",
    "status": "activated"
  },
  {
    "uid": 4256385120,
    "password": "jsnsjd_Z69WUKIE3VW",
    "account_id": "13713083098",
    "name": "gblike¹⁵⁵⁷⁸",
    "region": "BD",
    "status": "activated"
  },
  {
    "uid": 4256385063,
    "password": "jsnsjd_UNT9129FZJE",
    "account_id": "13713082952",
    "name": "gblike⁹²⁷⁴⁵",
    "region": "BD",
    "status": "activated"
  },
  {
    "uid": 4256385102,
    "password": "jsnsjd_VNHHNPZYIPL",
    "account_id": "13713083208",
    "name": "gblike⁵⁸¹²²",
    "region": "BD",
    "status": "activated"
  },
  {
    "uid": 4256384769,
    "password": "jsnsjd_FFEHSK5XH52",
    "account_id": "13713081282",
    "name": "gblike⁶⁰⁴⁸³",
    "region": "BD",
    "status": "activated"
  },
  {
    "uid": 4256385259,
    "password": "jsnsjd_KF6JZRAOUK6",
    "account_id": "13713083931",
    "name": "gblike⁹³³²⁰",
    "region": "BD",
    "status": "activated"
  },
  {
    "uid": 4256385284,
    "password": "jsnsjd_SR131U5P6ZF",
    "account_id": "13713083960",
    "name": "gblike⁶⁷³⁴⁸",
    "region": "BD",
    "status": "activated"
  },
  {
    "uid": 4256385451,
    "password": "jsnsjd_OQ5XIPR61H6",
    "account_id": "13713084890",
    "name": "gblike³³²¹¹",
    "region": "BD",
    "status": "activated"
  },
  {
    "uid": 4256385286,
    "password": "jsnsjd_QZ617CUT00I",
    "account_id": "13713084084",
    "name": "gblike⁸¹⁸⁰⁹",
    "region": "BD",
    "status": "activated"
  },
  {
    "uid": 4256385503,
    "password": "jsnsjd_4FPII0JSA5B",
    "account_id": "13713085083",
    "name": "gblike³⁹⁷⁴²",
    "region": "BD",
    "status": "activated"
  },
  {
    "uid": 4256385514,
    "password": "jsnsjd_90WGSLDUFBQ",
    "account_id": "13713085154",
    "name": "gblike⁸⁸⁹⁴²",
    "region": "BD",
    "status": "activated"
  },
  {
    "uid": 4256385710,
    "password": "jsnsjd_V9FTS7LVVN6",
    "account_id": "13713086178",
    "name": "gblike¹⁰⁹⁴⁹",
    "region": "BD",
    "status": "activated"
  },
  {
    "uid": 4256385707,
    "password": "jsnsjd_JKGHQXWYLW6",
    "account_id": "13713086250",
    "name": "gblike³²⁰⁸⁸",
    "region": "BD",
    "status": "activated"
  },
  {
    "uid": 4256385773,
    "password": "jsnsjd_T67BG45MQSY",
    "account_id": "13713086386",
    "name": "gblike⁷⁹⁵⁸⁰",
    "region": "BD",
    "status": "activated"
  },
  {
    "uid": 4256385959,
    "password": "jsnsjd_BSDG4TB221Z",
    "account_id": "13713087202",
    "name": "gblike⁹²²⁶⁰",
    "region": "BD",
    "status": "activated"
  },
  {
    "uid": 4256385960,
    "password": "jsnsjd_BISWW16FKVF",
    "account_id": "13713087275",
    "name": "gblike⁴⁵⁵⁴⁰",
    "region": "BD",
    "status": "activated"
  },
  {
    "uid": 4256385930,
    "password": "jsnsjd_17LZVRP2IK9",
    "account_id": "13713087102",
    "name": "gblike³⁹⁶⁰¹",
    "region": "BD",
    "status": "activated"
  },
  {
    "uid": 4256386113,
    "password": "jsnsjd_0KBX85JXHPI",
    "account_id": "13713088212",
    "name": "gblike⁰¹¹²⁵",
    "region": "BD",
    "status": "activated"
  },
  {
    "uid": 4256386153,
    "password": "jsnsjd_6IOS66KDTOL",
    "account_id": "13713088293",
    "name": "gblike²⁴⁰⁴⁴",
    "region": "BD",
    "status": "activated"
  },
  {
    "uid": 4256386151,
    "password": "jsnsjd_JIIU8P7K438",
    "account_id": "13713088319",
    "name": "gblike¹¹⁰⁹⁷",
    "region": "BD",
    "status": "activated"
  },
  {
    "uid": 4256386347,
    "password": "jsnsjd_CSSECBZ7AI8",
    "account_id": "13713089194",
    "name": "gblike⁹³²¹¹",
    "region": "BD",
    "status": "activated"
  },
  {
    "uid": 4256386344,
    "password": "jsnsjd_U8YLSY8LDBE",
    "account_id": "13713089176",
    "name": "gblike⁶⁰¹⁰¹",
    "region": "BD",
    "status": "activated"
  },
  {
    "uid": 4256386562,
    "password": "jsnsjd_XS0DEDXV6BQ",
    "account_id": "13713090282",
    "name": "gblike⁴²⁶⁷³",
    "region": "BD",
    "status": "activated"
  },
  {
    "uid": 4256386346,
    "password": "jsnsjd_8Y2NLXX84DA",
    "account_id": "13713089287",
    "name": "gblike⁹⁰⁹³⁸",
    "region": "BD",
    "status": "activated"
  },
  {
    "uid": 4256386558,
    "password": "jsnsjd_77XEPHSMIR6",
    "account_id": "13713090343",
    "name": "gblike⁰⁶⁶¹¹",
    "region": "BD",
    "status": "activated"
  },
  {
    "uid": 4256386528,
    "password": "jsnsjd_AZZHUUFRSOP",
    "account_id": "13713090352",
    "name": "gblike⁶⁶⁹³⁸",
    "region": "BD",
    "status": "activated"
  },
  {
    "uid": 4256386699,
    "password": "jsnsjd_E64Z0BOBED7",
    "account_id": "13713091164",
    "name": "gblike²⁸²⁴³",
    "region": "BD",
    "status": "activated"
  },
  {
    "uid": 4256386695,
    "password": "jsnsjd_L0F64LFR8B6",
    "account_id": "13713091173",
    "name": "gblike⁷⁰⁸⁷⁰",
    "region": "BD",
    "status": "activated"
  },
  {
    "uid": 4256387374,
    "password": "jsnsjd_N2OU8NJJOUH",
    "account_id": "13713094541",
    "name": "gblike⁵⁸⁴²³",
    "region": "BD",
    "status": "activated"
  },
  {
    "uid": 4256387348,
    "password": "jsnsjd_1RCPAZ7AGX1",
    "account_id": "13713094643",
    "name": "gblike⁷⁰⁶⁵⁹",
    "region": "BD",
    "status": "activated"
  },
  {
    "uid": 4256387592,
    "password": "jsnsjd_V0PRGH0WDK5",
    "account_id": "13713095524",
    "name": "gblike⁰³⁰⁷⁰",
    "region": "BD",
    "status": "activated"
  },
  {
    "uid": 4256387459,
    "password": "jsnsjd_13HJT7BV3B2",
    "account_id": "13713094842",
    "name": "gblike¹⁵⁸³⁴",
    "region": "BD",
    "status": "activated"
  },
  {
    "uid": 4256387609,
    "password": "jsnsjd_XWC5LQN4FSN",
    "account_id": "13713095608",
    "name": "gblike⁹⁸⁸⁷⁰",
    "region": "BD",
    "status": "activated"
  },
  {
    "uid": 4256387646,
    "password": "jsnsjd_XU37K1CYHIR",
    "account_id": "13713095829",
    "name": "gblike⁶⁸⁰⁸⁰",
    "region": "BD",
    "status": "activated"
  },
  {
    "uid": 4256387831,
    "password": "jsnsjd_CCSGSZOY3WP",
    "account_id": "13713096642",
    "name": "gblike⁸¹¹⁷⁶",
    "region": "BD",
    "status": "activated"
  },
  {
    "uid": 4256387815,
    "password": "jsnsjd_55TJBHO2Y07",
    "account_id": "13713096666",
    "name": "gblike⁸²⁵⁷⁵",
    "region": "BD",
    "status": "activated"
  },
  {
    "uid": 4256387865,
    "password": "jsnsjd_Y1RM2MPCVTI",
    "account_id": "13713096864",
    "name": "gblike⁴⁷⁵³²",
    "region": "BD",
    "status": "activated"
  },
  {
    "uid": 4256387983,
    "password": "jsnsjd_EZOKGU0I0N7",
    "account_id": "13713097387",
    "name": "gblike⁶⁵⁴⁰⁰",
    "region": "BD",
    "status": "activated"
  },
  {
    "uid": 4256388119,
    "password": "jsnsjd_NIC0YXJ214V",
    "account_id": "13713098049",
    "name": "gblike⁰⁵²⁹¹",
    "region": "BD",
    "status": "activated"
  },
  {
    "uid": 4256387989,
    "password": "jsnsjd_LXVL5VJEJEF",
    "account_id": "13713097497",
    "name": "gblike⁹¹⁹⁴²",
    "region": "BD",
    "status": "activated"
  },
  {
    "uid": 4256388040,
    "password": "jsnsjd_OYP5AHQPCYG",
    "account_id": "13713097817",
    "name": "gblike⁷⁴⁶⁸⁴",
    "region": "BD",
    "status": "activated"
  },
  {
    "uid": 4256388137,
    "password": "jsnsjd_PQM7NTENMXH",
    "account_id": "13713098109",
    "name": "gblike⁶³⁸⁸¹",
    "region": "BD",
    "status": "activated"
  },
  {
    "uid": 4256388223,
    "password": "jsnsjd_RO3NF4JO369",
    "account_id": "13713098715",
    "name": "gblike³²²⁵⁰",
    "region": "BD",
    "status": "activated"
  },
  {
    "uid": 4256388267,
    "password": "jsnsjd_O5YZJYBMJV8",
    "account_id": "13713099006",
    "name": "gblike⁸⁷¹²⁹",
    "region": "BD",
    "status": "activated"
  },
  {
    "uid": 4256388274,
    "password": "jsnsjd_L3FSAR08NOC",
    "account_id": "13713099081",
    "name": "gblike⁶⁵⁵³⁶",
    "region": "BD",
    "status": "activated"
  },
  {
    "uid": 4256388404,
    "password": "jsnsjd_81AGDK8BLGJ",
    "account_id": "13713099682",
    "name": "gblike⁰⁹²⁹⁵",
    "region": "BD",
    "status": "activated"
  },
  {
    "uid": 4256389270,
    "password": "jsnsjd_2S2YRELR09H",
    "account_id": "13713104659",
    "name": "gblike⁶⁴⁴⁶⁹",
    "region": "BD",
    "status": "activated"
  },
  {
    "uid": 4256388512,
    "password": "jsnsjd_CMR2AU6QXQO",
    "account_id": "13713100266",
    "name": "gblike⁷⁴³²⁰",
    "region": "BD",
    "status": "activated"
  },
  {
    "uid": 4256388451,
    "password": "jsnsjd_4C71FXITIB2",
    "account_id": "13713099954",
    "name": "gblike⁴⁵³⁰⁶",
    "region": "BD",
    "status": "activated"
  },
  {
    "uid": 4256389364,
    "password": "jsnsjd_Q1420JMS3GJ",
    "account_id": "13713105320",
    "name": "gblike¹¹⁵⁷⁹",
    "region": "BD",
    "status": "activated"
  },
  {
    "uid": 4256389313,
    "password": "jsnsjd_W0AR2M6E34O",
    "account_id": "13713104933",
    "name": "gblike⁵⁵⁹⁷²",
    "region": "BD",
    "status": "activated"
  },
  {
    "uid": 4256389461,
    "password": "jsnsjd_YUHYV1ESEKL",
    "account_id": "13713105602",
    "name": "gblike⁵⁴⁹²¹",
    "region": "BD",
    "status": "activated"
  },
  {
    "uid": 4256389572,
    "password": "jsnsjd_SI2N87WP94C",
    "account_id": "13713105859",
    "name": "gblike⁵⁹³⁴⁶",
    "region": "BD",
    "status": "activated"
  },
  {
    "uid": 4256389640,
    "password": "jsnsjd_G0D1INNES0X",
    "account_id": "13713106364",
    "name": "gblike⁹²⁶⁵²",
    "region": "BD",
    "status": "activated"
  },
  {
    "uid": 4256389672,
    "password": "jsnsjd_5QEIGS4RJNV",
    "account_id": "13713106521",
    "name": "gblike⁴⁷⁶⁹⁸",
    "region": "BD",
    "status": "activated"
  },
  {
    "uid": 4256389787,
    "password": "jsnsjd_2ADRJ1ZZXFK",
    "account_id": "13713107086",
    "name": "gblike⁶⁷¹⁶⁷",
    "region": "BD",
    "status": "activated"
  },
  {
    "uid": 4256389903,
    "password": "jsnsjd_Q0QZ7IMT0IR",
    "account_id": "13713107452",
    "name": "gblike¹¹⁴⁰²",
    "region": "BD",
    "status": "activated"
  },
  {
    "uid": 4256389864,
    "password": "jsnsjd_FDMXAWUZU4L",
    "account_id": "13713107539",
    "name": "gblike¹²¹⁹⁷",
    "region": "BD",
    "status": "activated"
  },
  {
    "uid": 4256389986,
    "password": "jsnsjd_MK52ZZCON4H",
    "account_id": "13713107815",
    "name": "gblike⁸¹⁰⁹⁴",
    "region": "BD",
    "status": "activated"
  },
  {
    "uid": 4256390080,
    "password": "jsnsjd_8LRMA7S8CLQ",
    "account_id": "13713108388",
    "name": "gblike⁸⁶²⁰⁶",
    "region": "BD",
    "status": "activated"
  },
  {
    "uid": 4256390103,
    "password": "jsnsjd_J6163H8ML9V",
    "account_id": "13713108578",
    "name": "gblike⁸³⁶⁰⁸",
    "region": "BD",
    "status": "activated"
  },
  {
    "uid": 4256390163,
    "password": "jsnsjd_7TO7UNROF15",
    "account_id": "13713108753",
    "name": "gblike²⁸⁷⁵⁰",
    "region": "BD",
    "status": "activated"
  },
  {
    "uid": 4256390324,
    "password": "jsnsjd_P5GQUTLF3E4",
    "account_id": "13713109620",
    "name": "gblike⁷²³⁹¹",
    "region": "BD",
    "status": "activated"
  },
  {
    "uid": 4256390289,
    "password": "jsnsjd_7538NALTTWE",
    "account_id": "13713109405",
    "name": "gblike⁸⁸⁹⁷⁵",
    "region": "BD",
    "status": "activated"
  },
  {
    "uid": 4256390443,
    "password": "jsnsjd_FHCR3IYUUQV",
    "account_id": "13713110213",
    "name": "gblike³⁹⁹³⁷",
    "region": "BD",
    "status": "activated"
  },
  {
    "uid": 4256390444,
    "password": "jsnsjd_AFFF55BQAV1",
    "account_id": "13713110354",
    "name": "gblike⁰⁸¹²⁰",
    "region": "BD",
    "status": "activated"
  },
  {
    "uid": 4256390504,
    "password": "jsnsjd_TOTWEW92B8K",
    "account_id": "13713110465",
    "name": "gblike⁸²⁷⁷⁷",
    "region": "BD",
    "status": "activated"
  },
  {
    "uid": 4256391394,
    "password": "jsnsjd_O1RNJL82LWR",
    "account_id": "13713115561",
    "name": "gblike⁸⁰²⁰⁶",
    "region": "BD",
    "status": "activated"
  },
  {
    "uid": 4256391430,
    "password": "jsnsjd_2VBDWBYRNAI",
    "account_id": "13713115735",
    "name": "gblike⁹⁴⁷³⁸",
    "region": "BD",
    "status": "activated"
  },
  {
    "uid": 4256390276,
    "password": "jsnsjd_QE1JLIN9ABV",
    "account_id": "13713109271",
    "name": "gblike⁸³⁵⁹⁷",
    "region": "BD",
    "status": "activated"
  },
  {
    "uid": 4256391564,
    "password": "jsnsjd_91R61VO4AFC",
    "account_id": "13713116481",
    "name": "gblike⁰⁶²⁹⁶",
    "region": "BD",
    "status": "activated"
  },
  {
    "uid": 4256391466,
    "password": "jsnsjd_TK11CWYA20J",
    "account_id": "13713116092",
    "name": "gblike⁵⁶⁴¹⁰",
    "region": "BD",
    "status": "activated"
  },
  {
    "uid": 4256391604,
    "password": "jsnsjd_83RSGJYUKU8",
    "account_id": "13713116610",
    "name": "gblike³⁵³⁷⁷",
    "region": "BD",
    "status": "activated"
  },
  {
    "uid": 4256391697,
    "password": "jsnsjd_FI06JYRL2IG",
    "account_id": "13713117123",
    "name": "gblike⁵⁷³²⁰",
    "region": "BD",
    "status": "activated"
  },
  {
    "uid": 4256391768,
    "password": "jsnsjd_1X1BNQ2U3NB",
    "account_id": "13713117527",
    "name": "gblike⁴⁸²¹³",
    "region": "BD",
    "status": "activated"
  },
  {
    "uid": 4256391786,
    "password": "jsnsjd_XSNCLK515NR",
    "account_id": "13713117603",
    "name": "gblike⁰¹²²⁶",
    "region": "BD",
    "status": "activated"
  },
  {
    "uid": 4256391842,
    "password": "jsnsjd_519P0LDR4O2",
    "account_id": "13713118064",
    "name": "gblike⁶⁸⁸⁸¹",
    "region": "BD",
    "status": "activated"
  },
  {
    "uid": 4256391923,
    "password": "jsnsjd_7BS55QPQXYN",
    "account_id": "13713118506",
    "name": "gblike³²⁵⁴⁷",
    "region": "BD",
    "status": "activated"
  },
  {
    "uid": 4256391964,
    "password": "jsnsjd_IRKI0MMTD56",
    "account_id": "13713118607",
    "name": "gblike⁹³⁰⁹⁸",
    "region": "BD",
    "status": "activated"
  },
  {
    "uid": 4256392110,
    "password": "jsnsjd_WCFIBHREIIN",
    "account_id": "13713119865",
    "name": "gblike¹³⁵⁰⁵",
    "region": "BD",
    "status": "activated"
  },
  {
    "uid": 4256392099,
    "password": "jsnsjd_GJK871L50HP",
    "account_id": "13713119964",
    "name": "gblike²⁷⁷⁵⁸",
    "region": "BD",
    "status": "activated"
  },
  {
    "uid": 4256392006,
    "password": "jsnsjd_LQ61WU395FU",
    "account_id": "13713118814",
    "name": "gblike⁹⁸⁹⁵⁴",
    "region": "BD",
    "status": "activated"
  },
  {
    "uid": 4256392178,
    "password": "jsnsjd_N1ELI5RJHUH",
    "account_id": "13713120077",
    "name": "gblike⁵⁰⁸¹⁹",
    "region": "BD",
    "status": "activated"
  },
  {
    "uid": 4256392338,
    "password": "jsnsjd_7P33RAF2HA6",
    "account_id": "13713120712",
    "name": "gblike¹¹³⁵⁸",
    "region": "BD",
    "status": "activated"
  },
  {
    "uid": 4256392323,
    "password": "jsnsjd_PINHFDYT2HU",
    "account_id": "13713120958",
    "name": "gblike⁸⁵⁰¹⁹",
    "region": "BD",
    "status": "activated"
  },
  {
    "uid": 4256392472,
    "password": "jsnsjd_EQQSSIM06KY",
    "account_id": "13713121595",
    "name": "gblike⁶⁴⁸¹⁰",
    "region": "BD",
    "status": "activated"
  },
  {
    "uid": 4256392531,
    "password": "jsnsjd_4CW101G6IMK",
    "account_id": "13713121941",
    "name": "gblike⁵¹⁸³⁵",
    "region": "BD",
    "status": "activated"
  },
  {
    "uid": 4256392364,
    "password": "jsnsjd_26EAN9F3KJO",
    "account_id": "13713121125",
    "name": "gblike²⁶³²⁵",
    "region": "BD",
    "status": "activated"
  },
  {
    "uid": 4256393325,
    "password": "jsnsjd_RGRQ9X03RYO",
    "account_id": "13713126129",
    "name": "gblike¹⁴⁰⁰⁰",
    "region": "BD",
    "status": "activated"
  },
  {
    "uid": 4256393345,
    "password": "jsnsjd_BNT6DKPWRK0",
    "account_id": "13713126238",
    "name": "gblike⁹⁹⁵⁴⁶",
    "region": "BD",
    "status": "activated"
  },
  {
    "uid": 4256393383,
    "password": "jsnsjd_BR0L24LU3HH",
    "account_id": "13713126343",
    "name": "gblike²⁸⁷¹⁴",
    "region": "BD",
    "status": "activated"
  }
]